fidding_cli-2.4.dist-info/METADATA
fidding_cli-2.4.dist-info/RECORD
fidding_cli-2.4.dist-info/WHEEL
fidding_cli-2.4.dist-info/entry_points.txt
fidding_cli-2.4.dist-info/top_level.txt
python-cli/__init__.py
python-cli/python_cli.py
python_cli/__init__.py
python_cli/data/data.txt
python_cli/script/__init__.py
python_cli/script/cli.py
